pycircadian/__init__.py
pycircadian/__main__.py
pycircadian/all_checks.py
pycircadian/config.py
pycircadian/cpu_load.py
pycircadian/idle_actions.py
pycircadian/idle_sessions.py
pycircadian/net_connections.py
pycircadian/process_block.py
pycircadian/sound_block.py
pycircadian-1.0.dist-info/LICENSE
pycircadian-1.0.dist-info/METADATA
pycircadian-1.0.dist-info/WHEEL
pycircadian-1.0.dist-info/entry_points.txt
pycircadian-1.0.dist-info/top_level.txt
pycircadian-1.0.dist-info/RECORD
